{
  "gunvan": {"text": "Нет данных.", "updated_at": "", "hash": "", "items": [], "sources": []},
  "dealers": {"text": "Нет данных.", "updated_at": "", "hash": "", "items": [], "sources": []},
  "stash": {"text": "Нет данных.", "updated_at": "", "hash": "", "items": [], "sources": []},
  "shipwreck": {"text": "Нет данных.", "updated_at": "", "hash": "", "items": [], "sources": []},
  "caches": {"text": "Нет данных.", "updated_at": "", "hash": "", "items": [], "sources": []},
  "news": {"text": "Нет данных.", "updated_at": "", "hash": "", "items": [], "sources": []},
  "weekly": {"text": "Нет данных.", "updated_at": "", "hash": "", "items": [], "sources": []}
}
